test_gen/__init__.py
test_gen/__main__.py
test_gen/test_repo.py
testfoundry-0.1.dist-info/LICENSE
testfoundry-0.1.dist-info/METADATA
testfoundry-0.1.dist-info/WHEEL
testfoundry-0.1.dist-info/entry_points.txt
testfoundry-0.1.dist-info/top_level.txt
testfoundry-0.1.dist-info/RECORD
