Metadata-Version: 2.1
Name: testfoundry
Version: 0.1
Summary: A Python test generator
Home-page: https://github.com/KDreynolds/py_testgen
Author: Kyle Reynolds
Author-email: kylereynoldsdev@gmail.com
License: UNKNOWN
Platform: UNKNOWN
Classifier: Development Status :: 3 - Alpha
Classifier: Intended Audience :: Developers
Classifier: License :: OSI Approved :: MIT License
Classifier: Programming Language :: Python :: 3.6
Classifier: Programming Language :: Python :: 3.7
Classifier: Programming Language :: Python :: 3.8
Classifier: Programming Language :: Python :: 3.9
